{
  "kit-rma": {
    "general": {
      "moduleTitle": "KIT RMA",
      "description": "Klarsicht IT",
      "ticketTitle": "Tickets",
      "caseTitle": "Geschäftsfall",
      "textTitle": "Abschnitt",
      "statusTitle": "Status",
      "addressbookTitle": "Adressbuch",
      "messageEmpty": "Keine Aufzeichnungen",
      "delete": "Löschen",
      "cancelButtonText": "Abbrechen",
      "viewListButton": "Liste anzeigen",
      "saveButtonText": "Save",
      "create": "Neu",
      "reset": "Zurücksetzen",
      "filters": "Filter",
      "sendButtonText": "Senden"
    },
    "modules": {
      "ticket": {
        "title": "Ticket",
        "new": "Neues Ticket erstellen",
        "list": "Tickets ansehen",
        "name": "Name",
        "order": "Bestellung",
        "customer": "Kunde",
        "customerNumber": "Kundennummer",
        "customerEmail": "Kunden-E-Mail",
        "product": "Produkt",
        "productName": "Produktname",
        "productNumber": "Produktnummer",
        "enterProductNumber": "Produktnummer eingeben",
        "selectProduct": "Select product",
        "amount": "Betrag",
        "amountTotal": "Betrag Gesamt",
        "quantity": "Menge",
        "status": "Status",
        "user": "Benutzer",
        "createdAt": "Datum",
        "orderDate": "Bestellung aufgegeben am",
        "case": "Geschäftsfall",
        "freetextfieldsTitle": "Infos zum Geschäftsfall",
        "feeCustomer": "Gebühren (Kunde)",
        "feeSupplier": "Gebühren (Lieferant)",
        "supplier": "Lieferant",
        "files": "Dateien",
        "link": "Link",
        "kitVoucher": "KIT-Gutschein",
        "returnAddress": "Rücksendeadresse",
        "additionalInfo": "Zusätzliche Informationen",
        "badges": "Abzeichen",
        "supplierVoucher": "Reservierungsnummer Ersatzware",
        "supplierRmaNumber": "Lieferanten-RMA-Nummer",
        "history": "Vorgeschichte",
        "attachment": "Anhänge",
        "communication": "Kommunikation",
        "messageType": "Nachrichtentyp",
        "snippet": "Textausschnitt",
        "message": "Nachricht",
        "rmaNumber": "RMA #",
        "confirmDelete": "Sind Sie sicher? Ein einmal gelöschter Datensatz kann nicht wiederhergestellt werden. ",
        "pdfHelp": "Produktname und RMA-Nummer des Lieferanten sind erforderlich, um das PDF zu erzeugen",
        "open": "Offene Tickets",
        "customerHelpText": "Wenn Sie die Auftragsnummer kennen, geben Sie diese bitte in das Auftragsfeld ein und der Kunde wird automatisch ausgewählt",
        "pvg": "Aktueller PVG Preis (brutto)",
        "gross": "Aktueller STD Preis (brutto)",
        "stock": "Aktueller Bestand",
        "serialNumber": "Seriennummer",
        "selectSerialNumber": "Select seriennummer"
      },
      "address": {
        "title": "Adressbuch",
        "new": "Neue Adresse anlegen",
        "list": "Adressen ansehen",
        "name": "Name",
        "addressLabel": "Adresse",
        "supplierLabel": "Zulieferer"
      },
      "case": {
        "title": "Geschäftsfall",
        "new": "Neuen Geschäftsfall erstellen",
        "list": "Geschäftsfälle anzeigen",
        "addFreetext": "Neuer Freitext",
        "name": "Name",
        "freetext": {
          "title": "Titel",
          "fieldType": "Feld Typ",
          "explanation": "Erläuterung",
          "required": "Erforderlich (Kunde)",
          "requiredAdmin": "Erforderlich (Admin)",
          "amountDepend": "Abhängig vom Betrag",
          "valuesLabel": "Werte",
          "valuesHelptext": "Komma getrennte Werte eingeben"
        }
      },
      "text": {
        "title": "Textausschnitt",
        "new": "Neues Text-Snippet erstellen",
        "list": "Textschnipsel anzeigen",
        "name": "Name",
        "typeLabel": "Typ",
        "snippetLabel": "Beschreibung",
        "placeholderLabel": "Platzhalter einfügen",
        "help": "Wählen Sie die verfügbaren Platzhalter aus, die bei der Ausführung für die Verwendung im Text ersetzt werden sollen"
      },
      "status": {
        "title": "Status",
        "new": "Neuen Status erstellen",
        "list": "Zustände anzeigen",
        "name": "Name",
        "nameExtLabel": "Name Extern",
        "endstateLabel": "Endstate",
        "endstateFinalLabel": "Endstadium Endgültig",
        "colorLabel": "Farbe"
      }
    }
  }
}
